{
  "updated": "2026-03-10 07:24:26 AM ET",
  "data": {
    "BTC": {
      "symbol": "BTC",
      "slug": "btc-updown-15m",
      "condition_id": "0xd6bd1a063d03619d7449b6db5781551fe4499cafcc02bd62cc062d0f206aceb3",
      "elapsed_pct": 0.6292,
      "remaining_sec": 333.7,
      "up_price": 0.9,
      "down_price": 0.1,
      "arb": null,
      "rv60": 6.873801,
      "eff60": 0.039,
      "vol_bucket": "HighVol",
      "trend_bucket": "Trend",
      "spread": 1.96,
      "dir_60pct": 0.852,
      "dir_80pct": 0.896,
      "dir_90pct": 0.918,
      "prob_008": 0.36,
      "prob_012": 0.47,
      "prob_020": 0.63
    },
    "ETH": {
      "symbol": "ETH",
      "slug": "eth-updown-15m",
      "condition_id": "0x8fb841d6515709a3198bca8b64e48ddbc4d989a361f23d072c0aeb2f9fa821c3",
      "elapsed_pct": 0.6292,
      "remaining_sec": 333.7,
      "up_price": 0.02,
      "down_price": 0.98,
      "arb": null,
      "rv60": 17.961691,
      "eff60": 0.001,
      "vol_bucket": "HighVol",
      "trend_bucket": "Range",
      "spread": 1.96,
      "dir_60pct": 0.1928,
      "dir_80pct": 0.1544,
      "dir_90pct": 0.1352,
      "prob_008": 0.44,
      "prob_012": 0.56,
      "prob_020": 0.71
    },
    "SOL": {
      "symbol": "SOL",
      "slug": "sol-updown-15m",
      "condition_id": "0xd43bce8509b5ccffa0b9320f4d61c5d4a76437207d047bfd584643eccbb128dd",
      "elapsed_pct": 0.6292,
      "remaining_sec": 333.7,
      "up_price": 0.95,
      "down_price": 0.05,
      "arb": null,
      "rv60": 11.925109,
      "eff60": 0.0187,
      "vol_bucket": "HighVol",
      "trend_bucket": "Range",
      "spread": 1.96,
      "dir_60pct": 0.788,
      "dir_80pct": 0.824,
      "dir_90pct": 0.842,
      "prob_008": 0.44,
      "prob_012": 0.56,
      "prob_020": 0.71
    },
    "XRP": {
      "symbol": "XRP",
      "slug": "xrp-updown-15m",
      "condition_id": "0x8d862deb63c8d6e07f3a58355919aa8fad3052909b263a9b3c5a76101e9560b4",
      "elapsed_pct": 0.6292,
      "remaining_sec": 333.7,
      "up_price": 0.64,
      "down_price": 0.36,
      "arb": null,
      "rv60": 2.642476,
      "eff60": 0.0412,
      "vol_bucket": "LowVol",
      "trend_bucket": "Trend",
      "spread": 1.96,
      "dir_60pct": 0.6176,
      "dir_80pct": 0.6323,
      "dir_90pct": 0.6397,
      "prob_008": 0.52,
      "prob_012": 0.63,
      "prob_020": 0.8
    }
  }
}