{
  "updated": "2026-03-10 01:08:19 PM ET",
  "data": {
    "BTC": {
      "symbol": "BTC",
      "slug": "btc-updown-15m",
      "condition_id": "0x06173eabe0e8e27b7a093deb2fb2a070d05cd24ce06dc159cb1fd2a4d9bd2535",
      "elapsed_pct": 0.5546,
      "remaining_sec": 400.8,
      "up_price": 0.65,
      "down_price": 0.35,
      "arb": null,
      "rv60": 4.818276,
      "eff60": 0.0125,
      "vol_bucket": "HighVol",
      "trend_bucket": "Trend",
      "spread": 1.96,
      "dir_60pct": 0.632,
      "dir_80pct": 0.6485,
      "dir_90pct": 0.6568,
      "prob_008": 0.36,
      "prob_012": 0.47,
      "prob_020": 0.63
    },
    "ETH": {
      "symbol": "ETH",
      "slug": "eth-updown-15m",
      "condition_id": "0x167ebb9847698cb6fdde959ad0b3e4c6d3a54c0bdf821a67959a75b1418ab29d",
      "elapsed_pct": 0.5546,
      "remaining_sec": 400.8,
      "up_price": 0.44,
      "down_price": 0.56,
      "arb": null,
      "rv60": 4.5329,
      "eff60": 0.0143,
      "vol_bucket": "HighVol",
      "trend_bucket": "Range",
      "spread": 0.04,
      "dir_60pct": 0.4616,
      "dir_80pct": 0.4568,
      "dir_90pct": 0.4544,
      "prob_008": 0.44,
      "prob_012": 0.56,
      "prob_020": 0.71
    },
    "SOL": {
      "symbol": "SOL",
      "slug": "sol-updown-15m",
      "condition_id": "0x9f80a5b22a0aa832a01c21b2d86d16b71f43d26c9fc43afcdd9b51fb17d82a28",
      "elapsed_pct": 0.5546,
      "remaining_sec": 400.8,
      "up_price": 0.655,
      "down_price": 0.345,
      "arb": null,
      "rv60": 7.397008,
      "eff60": 0.022,
      "vol_bucket": "HighVol",
      "trend_bucket": "Range",
      "spread": 0.02,
      "dir_60pct": 0.5992,
      "dir_80pct": 0.6116,
      "dir_90pct": 0.6178,
      "prob_008": 0.44,
      "prob_012": 0.56,
      "prob_020": 0.71
    },
    "XRP": {
      "symbol": "XRP",
      "slug": "xrp-updown-15m",
      "condition_id": "0x3228b1abf58c4a5b443d5545d8bb1419439f847c6541ce50b6cebe3004dd593c",
      "elapsed_pct": 0.5546,
      "remaining_sec": 400.8,
      "up_price": 0.485,
      "down_price": 0.515,
      "arb": null,
      "rv60": 4.41135,
      "eff60": 0.0122,
      "vol_bucket": "HighVol",
      "trend_bucket": "Range",
      "spread": 0.14,
      "dir_60pct": 0.4904,
      "dir_80pct": 0.4892,
      "dir_90pct": 0.4886,
      "prob_008": 0.44,
      "prob_012": 0.56,
      "prob_020": 0.71
    }
  }
}