{
  "updated": "2026-03-13 11:31:20 PM ET",
  "data": {
    "BTC": {
      "symbol": "BTC",
      "slug": "btc-updown-15m",
      "condition_id": "0x6e9e30ed806fa7f13b666575934693992309b620ca64a5a9db350b6366c247e9",
      "elapsed_pct": 0.0891,
      "remaining_sec": 819.8,
      "up_price": 0.45,
      "down_price": 0.55,
      "arb": null,
      "rv60": 7.837187,
      "eff60": 0.0291,
      "vol_bucket": "HighVol",
      "trend_bucket": "Trend",
      "spread": 1.96,
      "dir_60pct": 0.456,
      "dir_80pct": 0.4505,
      "dir_90pct": 0.4477,
      "prob_008": 0.36,
      "prob_012": 0.47,
      "prob_020": 0.63
    },
    "ETH": {
      "symbol": "ETH",
      "slug": "eth-updown-15m",
      "condition_id": "0x28214309f18717ba745bcbbade33536584917050131f41cfb884f2bc85c5baa9",
      "elapsed_pct": 0.0891,
      "remaining_sec": 819.8,
      "up_price": 0.43,
      "down_price": 0.57,
      "arb": null,
      "rv60": 5.045074,
      "eff60": 0.0182,
      "vol_bucket": "HighVol",
      "trend_bucket": "Trend",
      "spread": 1.96,
      "dir_60pct": 0.4384,
      "dir_80pct": 0.4307,
      "dir_90pct": 0.4269,
      "prob_008": 0.36,
      "prob_012": 0.47,
      "prob_020": 0.63
    },
    "SOL": {
      "symbol": "SOL",
      "slug": "sol-updown-15m",
      "condition_id": "0x37e4f0e9577617aac15e9fe052c990a461faa7f3ae4fc88e65c5b0945c382fb5",
      "elapsed_pct": 0.0891,
      "remaining_sec": 819.8,
      "up_price": 0.46,
      "down_price": 0.54,
      "arb": null,
      "rv60": 8.18438,
      "eff60": 0.0028,
      "vol_bucket": "HighVol",
      "trend_bucket": "Range",
      "spread": 1.96,
      "dir_60pct": 0.4744,
      "dir_80pct": 0.4712,
      "dir_90pct": 0.4696,
      "prob_008": 0.44,
      "prob_012": 0.56,
      "prob_020": 0.71
    },
    "XRP": {
      "symbol": "XRP",
      "slug": "xrp-updown-15m",
      "condition_id": "0x33ac73e4ea5844d69d4d704747f2a29fb7fa8d010bd828329e9ca20a2de9e2d5",
      "elapsed_pct": 0.0891,
      "remaining_sec": 819.8,
      "up_price": 0.35,
      "down_price": 0.65,
      "arb": null,
      "rv60": 10.053549,
      "eff60": 0.0084,
      "vol_bucket": "HighVol",
      "trend_bucket": "Range",
      "spread": 1.96,
      "dir_60pct": 0.404,
      "dir_80pct": 0.392,
      "dir_90pct": 0.386,
      "prob_008": 0.44,
      "prob_012": 0.56,
      "prob_020": 0.71
    }
  }
}