{
  "updated": "2026-03-15 08:26 AM ET",
  "data": {
    "BTC": {
      "symbol": "BTC",
      "slug": "btc-updown-15m-1773576900",
      "condition_id": "0x861f9d5a0728cd5537ba8855b883aa390df5ba40e2cc1046c09a44c6021c4843",
      "elapsed_pct": 0.7351,
      "remaining_sec": 238.4,
      "up_price": 0.605,
      "down_price": 0.395,
      "arb": null,
      "rv60": 643.02513,
      "eff60": 0.008,
      "vol_bucket": "HighVol",
      "trend_bucket": "Range",
      "spread": 98,
      "dir_60pct": 0.5656,
      "dir_80pct": 0.5702,
      "dir_90pct": 0.5749,
      "prob_008": 0.59,
      "prob_012": 0.6,
      "prob_020": 0.67
    },
    "ETH": {
      "symbol": "ETH",
      "slug": "eth-updown-15m-1773576900",
      "condition_id": "0x57dfee8bdc95bb78e3eb57f4a44ce25d5a8ad5ec28b2980d23ced952b19c2353",
      "elapsed_pct": 0.7351,
      "remaining_sec": 238.4,
      "up_price": 0.685,
      "down_price": 0.315,
      "arb": null,
      "rv60": 470.88837,
      "eff60": 0.014,
      "vol_bucket": "HighVol",
      "trend_bucket": "Range",
      "spread": 98,
      "dir_60pct": 0.6156,
      "dir_80pct": 0.6237,
      "dir_90pct": 0.6319,
      "prob_008": 0.67,
      "prob_012": 0.69,
      "prob_020": 0.75
    },
    "SOL": {
      "symbol": "SOL",
      "slug": "sol-updown-15m-1773576900",
      "condition_id": "0x72731fdda5dff2802df0babd5d389f79d6194fc7d4ebee63cbbbeed5b7c7c5f7",
      "elapsed_pct": 0.7351,
      "remaining_sec": 238.4,
      "up_price": 0.485,
      "down_price": 0.515,
      "arb": null,
      "rv60": 537.04166,
      "eff60": 0.007,
      "vol_bucket": "HighVol",
      "trend_bucket": "Range",
      "spread": 98,
      "dir_60pct": 0.4906,
      "dir_80pct": 0.49,
      "dir_90pct": 0.4893,
      "prob_008": 0.49,
      "prob_012": 0.48,
      "prob_020": 0.53
    },
    "XRP": {
      "symbol": "XRP",
      "slug": "xrp-updown-15m-1773576900",
      "condition_id": "0xca6cc576f113f1b29952cb1c3af6866c890ea19d2b10723fb6d48b287db42737",
      "elapsed_pct": 0.7351,
      "remaining_sec": 238.4,
      "up_price": 0.165,
      "down_price": 0.835,
      "arb": null,
      "rv60": 530.52048,
      "eff60": 0.076,
      "vol_bucket": "HighVol",
      "trend_bucket": "Trend",
      "spread": 99.8,
      "dir_60pct": 0.2907,
      "dir_80pct": 0.2759,
      "dir_90pct": 0.2611,
      "prob_008": 0.2,
      "prob_012": 0.17,
      "prob_020": 0.18
    }
  }
}