{
  "updated": "2026-03-05 09:57:30 PM ET",
  "data": {
    "BTC": {
      "symbol": "BTC",
      "slug": "btc-updown-15m",
      "condition_id": "0xd7a5182d975fb78d8c2a2ef475772f6dd9de4866a6b2ccf73b0e05befa8dec99",
      "elapsed_pct": 0.8341,
      "remaining_sec": 149.3,
      "up_price": 0.01,
      "down_price": 0.99,
      "arb": null,
      "rv60": 14.027942,
      "eff60": 0.0056,
      "vol_bucket": "HighVol",
      "trend_bucket": "Range",
      "spread": 1.96,
      "dir_60pct": 0.1864,
      "dir_80pct": 0.1472,
      "dir_90pct": 0.1276,
      "prob_008": 0.44,
      "prob_012": 0.56,
      "prob_020": 0.71
    },
    "ETH": {
      "symbol": "ETH",
      "slug": "eth-updown-15m",
      "condition_id": "0x32796cc5d1c7ba9f73a9d5f4bc2bdce21e12aea46846fc58e523776945c95116",
      "elapsed_pct": 0.8341,
      "remaining_sec": 149.3,
      "up_price": 0.001,
      "down_price": 0.999,
      "arb": null,
      "rv60": 21.143223,
      "eff60": 0.0208,
      "vol_bucket": "HighVol",
      "trend_bucket": "Trend",
      "spread": 1.996,
      "dir_60pct": 0.0609,
      "dir_80pct": 0.006,
      "dir_90pct": 0.0,
      "prob_008": 0.36,
      "prob_012": 0.47,
      "prob_020": 0.63
    },
    "SOL": {
      "symbol": "SOL",
      "slug": "sol-updown-15m",
      "condition_id": "0xd47721c3acb5cce5e714d079d8144229a996451db2bf54ee2c23de0f66743bcd",
      "elapsed_pct": 0.8341,
      "remaining_sec": 149.3,
      "up_price": 0.98,
      "down_price": 0.02,
      "arb": null,
      "rv60": 18.499921,
      "eff60": 0.0195,
      "vol_bucket": "HighVol",
      "trend_bucket": "Trend",
      "spread": 0.0,
      "dir_60pct": 0.9224,
      "dir_80pct": 0.9752,
      "dir_90pct": 1.0,
      "prob_008": 0.36,
      "prob_012": 0.47,
      "prob_020": 0.63
    },
    "XRP": {
      "symbol": "XRP",
      "slug": "xrp-updown-15m",
      "condition_id": "0x59aefdd7e49fbb30d23e578550cadb7f6460d1657f10a78c43efd902f3f3adf5",
      "elapsed_pct": 0.8341,
      "remaining_sec": 149.3,
      "up_price": 0.98,
      "down_price": 0.02,
      "arb": null,
      "rv60": 13.981085,
      "eff60": 0.0407,
      "vol_bucket": "HighVol",
      "trend_bucket": "Trend",
      "spread": 0.0,
      "dir_60pct": 0.9224,
      "dir_80pct": 0.9752,
      "dir_90pct": 1.0,
      "prob_008": 0.36,
      "prob_012": 0.47,
      "prob_020": 0.63
    }
  }
}