{
  "updated": "2026-03-06 03:33:36 PM ET",
  "data": {
    "BTC": {
      "symbol": "BTC",
      "slug": "btc-updown-15m",
      "condition_id": "0x719853847fbbfec53a6ee34ed4582aafaabf3fff6c65e2542de5f91bcd11e961",
      "elapsed_pct": 0.2406,
      "remaining_sec": 683.5,
      "up_price": 0.54,
      "down_price": 0.46,
      "arb": null,
      "rv60": 2.346153,
      "eff60": 0.016,
      "vol_bucket": "LowVol",
      "trend_bucket": "Range",
      "spread": 1.96,
      "dir_60pct": 0.5288,
      "dir_80pct": 0.5324,
      "dir_90pct": 0.5342,
      "prob_008": 0.65,
      "prob_012": 0.74,
      "prob_020": 0.87
    },
    "ETH": {
      "symbol": "ETH",
      "slug": "eth-updown-15m",
      "condition_id": "0x25c112a5d60ab44e8fff3575194b6ebd008dcd9b6d83bec196f363fb23085e57",
      "elapsed_pct": 0.2406,
      "remaining_sec": 683.5,
      "up_price": 0.6,
      "down_price": 0.4,
      "arb": null,
      "rv60": 1.425367,
      "eff60": 0.0074,
      "vol_bucket": "LowVol",
      "trend_bucket": "Range",
      "spread": 1.96,
      "dir_60pct": 0.572,
      "dir_80pct": 0.581,
      "dir_90pct": 0.5855,
      "prob_008": 0.65,
      "prob_012": 0.74,
      "prob_020": 0.87
    },
    "SOL": {
      "symbol": "SOL",
      "slug": "sol-updown-15m",
      "condition_id": "0x6033a8461dde2327e19e38530773bcabefc8261f6df05efc68be2deed0ffc82a",
      "elapsed_pct": 0.2406,
      "remaining_sec": 683.5,
      "up_price": 0.39,
      "down_price": 0.61,
      "arb": null,
      "rv60": 0.69159,
      "eff60": 0.0643,
      "vol_bucket": "LowVol",
      "trend_bucket": "Trend",
      "spread": 1.96,
      "dir_60pct": 0.4076,
      "dir_80pct": 0.3961,
      "dir_90pct": 0.3903,
      "prob_008": 0.52,
      "prob_012": 0.63,
      "prob_020": 0.8
    },
    "XRP": {
      "symbol": "XRP",
      "slug": "xrp-updown-15m",
      "condition_id": "0x01c8d3de75ab7e8aa45aa2004e3fda23268acc74c98a37c22ec00504bef1ec49",
      "elapsed_pct": 0.2406,
      "remaining_sec": 683.5,
      "up_price": 0.58,
      "down_price": 0.42,
      "arb": null,
      "rv60": 1.079123,
      "eff60": 0.0523,
      "vol_bucket": "LowVol",
      "trend_bucket": "Trend",
      "spread": 1.96,
      "dir_60pct": 0.5672,
      "dir_80pct": 0.5756,
      "dir_90pct": 0.5798,
      "prob_008": 0.52,
      "prob_012": 0.63,
      "prob_020": 0.8
    }
  }
}