{
  "updated": "2026-03-11 11:50:46 PM ET",
  "data": {
    "BTC": {
      "symbol": "BTC",
      "slug": "btc-updown-15m",
      "condition_id": "0xdf63e3ea89f50aa495877b13629148eff064909f10b87533a7df43f5ff4fa70c",
      "elapsed_pct": 0.3852,
      "remaining_sec": 553.3,
      "up_price": 0.87,
      "down_price": 0.13,
      "arb": null,
      "rv60": 10.661564,
      "eff60": 0.0,
      "vol_bucket": "HighVol",
      "trend_bucket": "Range",
      "spread": 1.96,
      "dir_60pct": 0.7368,
      "dir_80pct": 0.7664,
      "dir_90pct": 0.7812,
      "prob_008": 0.44,
      "prob_012": 0.56,
      "prob_020": 0.71
    },
    "ETH": {
      "symbol": "ETH",
      "slug": "eth-updown-15m",
      "condition_id": "0x3d7df6abdc6245e0f9382b07ffc11241a85ddb112018253ba94ae0d9c9fcbc10",
      "elapsed_pct": 0.3852,
      "remaining_sec": 553.3,
      "up_price": 0.03,
      "down_price": 0.97,
      "arb": null,
      "rv60": 16.450706,
      "eff60": 0.0,
      "vol_bucket": "HighVol",
      "trend_bucket": "Range",
      "spread": 1.96,
      "dir_60pct": 0.1992,
      "dir_80pct": 0.1616,
      "dir_90pct": 0.1428,
      "prob_008": 0.44,
      "prob_012": 0.56,
      "prob_020": 0.71
    },
    "SOL": {
      "symbol": "SOL",
      "slug": "sol-updown-15m",
      "condition_id": "0xa723a8edd989070dcb6f0449a9e61b1502f3c646040e35cd3592073a895c5ad9",
      "elapsed_pct": 0.3852,
      "remaining_sec": 553.3,
      "up_price": 0.961,
      "down_price": 0.039,
      "arb": null,
      "rv60": 13.822947,
      "eff60": 0.0411,
      "vol_bucket": "HighVol",
      "trend_bucket": "Trend",
      "spread": 1.96,
      "dir_60pct": 0.9057,
      "dir_80pct": 0.9564,
      "dir_90pct": 0.9817,
      "prob_008": 0.36,
      "prob_012": 0.47,
      "prob_020": 0.63
    },
    "XRP": {
      "symbol": "XRP",
      "slug": "xrp-updown-15m",
      "condition_id": "0xeeddff7e124333abdb6ba88a23d868cbdcfec6086ed170e0f062c999d6a5754b",
      "elapsed_pct": 0.3852,
      "remaining_sec": 553.3,
      "up_price": 0.12,
      "down_price": 0.88,
      "arb": null,
      "rv60": 12.181713,
      "eff60": 0.0176,
      "vol_bucket": "HighVol",
      "trend_bucket": "Range",
      "spread": 1.96,
      "dir_60pct": 0.2568,
      "dir_80pct": 0.2264,
      "dir_90pct": 0.2112,
      "prob_008": 0.44,
      "prob_012": 0.56,
      "prob_020": 0.71
    }
  }
}