{
  "updated": "2026-03-06 07:55:33 AM ET",
  "data": {
    "BTC": {
      "symbol": "BTC",
      "slug": "btc-updown-15m",
      "condition_id": "0xb9155233591b745563ecbcfae7cc225fae1744f156dc63a5dbec252552fa0f46",
      "elapsed_pct": 0.704,
      "remaining_sec": 266.4,
      "up_price": 0.97,
      "down_price": 0.03,
      "arb": null,
      "rv60": 9.486258,
      "eff60": 0.0188,
      "vol_bucket": "LowVol",
      "trend_bucket": "Range",
      "spread": 1.96,
      "dir_60pct": 0.8384,
      "dir_80pct": 0.8807,
      "dir_90pct": 0.9019,
      "prob_008": 0.65,
      "prob_012": 0.74,
      "prob_020": 0.87
    },
    "ETH": {
      "symbol": "ETH",
      "slug": "eth-updown-15m",
      "condition_id": "0x670d3f013151cf461653f8b49d95327f9ddb4300abf673e7adb0c91bbbc8634a",
      "elapsed_pct": 0.704,
      "remaining_sec": 266.4,
      "up_price": 0.06,
      "down_price": 0.94,
      "arb": null,
      "rv60": 10.214411,
      "eff60": 0.0239,
      "vol_bucket": "LowVol",
      "trend_bucket": "Trend",
      "spread": 1.96,
      "dir_60pct": 0.1304,
      "dir_80pct": 0.0842,
      "dir_90pct": 0.0611,
      "prob_008": 0.52,
      "prob_012": 0.63,
      "prob_020": 0.8
    },
    "SOL": {
      "symbol": "SOL",
      "slug": "sol-updown-15m",
      "condition_id": "0xe493ce1f8bc0dc7fff1a151de051a6eb758a96b7633afb75f7504f0f8b2c45f0",
      "elapsed_pct": 0.704,
      "remaining_sec": 266.4,
      "up_price": 0.83,
      "down_price": 0.17,
      "arb": null,
      "rv60": 4.472944,
      "eff60": 0.0251,
      "vol_bucket": "LowVol",
      "trend_bucket": "Trend",
      "spread": 1.96,
      "dir_60pct": 0.7772,
      "dir_80pct": 0.8118,
      "dir_90pct": 0.8292,
      "prob_008": 0.52,
      "prob_012": 0.63,
      "prob_020": 0.8
    },
    "XRP": {
      "symbol": "XRP",
      "slug": "xrp-updown-15m",
      "condition_id": "0xce4a1464b58591a682940a63f685853763b13d02d7051a82cdbe5f97b52323f4",
      "elapsed_pct": 0.704,
      "remaining_sec": 266.4,
      "up_price": 0.12,
      "down_price": 0.88,
      "arb": null,
      "rv60": 6.17891,
      "eff60": 0.0,
      "vol_bucket": "LowVol",
      "trend_bucket": "Range",
      "spread": 1.96,
      "dir_60pct": 0.2264,
      "dir_80pct": 0.1922,
      "dir_90pct": 0.1751,
      "prob_008": 0.65,
      "prob_012": 0.74,
      "prob_020": 0.87
    }
  }
}