{
  "updated": "2026-03-07 01:57:10 AM ET",
  "data": {
    "BTC": {
      "symbol": "BTC",
      "slug": "btc-updown-15m",
      "condition_id": "0x1884ccebf4d5c4ac9ae5a866d5f0e642f6b7e49a9e1113cbc668907d8aaa53f6",
      "elapsed_pct": 0.8116,
      "remaining_sec": 169.6,
      "up_price": 0.005,
      "down_price": 0.995,
      "arb": null,
      "rv60": 24.002906,
      "eff60": 0.0201,
      "vol_bucket": "HighVol",
      "trend_bucket": "Trend",
      "spread": 1.996,
      "dir_60pct": 0.0644,
      "dir_80pct": 0.0099,
      "dir_90pct": 0.0,
      "prob_008": 0.36,
      "prob_012": 0.47,
      "prob_020": 0.63
    },
    "ETH": {
      "symbol": "ETH",
      "slug": "eth-updown-15m",
      "condition_id": "0x746200d5afe4e9ccca209e560d83d90418b86423ed764e966dc26b967425283a",
      "elapsed_pct": 0.8116,
      "remaining_sec": 169.6,
      "up_price": 0.03,
      "down_price": 0.97,
      "arb": null,
      "rv60": 18.390185,
      "eff60": 0.0195,
      "vol_bucket": "HighVol",
      "trend_bucket": "Trend",
      "spread": 1.96,
      "dir_60pct": 0.0864,
      "dir_80pct": 0.0347,
      "dir_90pct": 0.0089,
      "prob_008": 0.36,
      "prob_012": 0.47,
      "prob_020": 0.63
    },
    "SOL": {
      "symbol": "SOL",
      "slug": "sol-updown-15m",
      "condition_id": "0xeacba5f1e810d5ca37326813988bdbbc4718566b95cfbca0bef6fabd4e9e4e89",
      "elapsed_pct": 0.8116,
      "remaining_sec": 169.6,
      "up_price": 0.02,
      "down_price": 0.98,
      "arb": null,
      "rv60": 16.246201,
      "eff60": 0.004,
      "vol_bucket": "HighVol",
      "trend_bucket": "Range",
      "spread": 1.96,
      "dir_60pct": 0.1928,
      "dir_80pct": 0.1544,
      "dir_90pct": 0.1352,
      "prob_008": 0.44,
      "prob_012": 0.56,
      "prob_020": 0.71
    },
    "XRP": {
      "symbol": "XRP",
      "slug": "xrp-updown-15m",
      "condition_id": "0x4779225c40a283d29e6d31c24042a497da654b194a132d0593d01bb2d4e110e6",
      "elapsed_pct": 0.8116,
      "remaining_sec": 169.6,
      "up_price": 0.04,
      "down_price": 0.96,
      "arb": null,
      "rv60": 11.569935,
      "eff60": 0.0201,
      "vol_bucket": "HighVol",
      "trend_bucket": "Trend",
      "spread": 1.96,
      "dir_60pct": 0.0952,
      "dir_80pct": 0.0446,
      "dir_90pct": 0.0193,
      "prob_008": 0.36,
      "prob_012": 0.47,
      "prob_020": 0.63
    }
  }
}