{
  "updated": "2026-03-06 02:43:19 PM ET",
  "data": {
    "BTC": {
      "symbol": "BTC",
      "slug": "btc-updown-15m",
      "condition_id": "0x8e39406ebe1cf0dc131ba32b722db14addf1b37f5a12ed379692427822ba4ca3",
      "elapsed_pct": 0.8878,
      "remaining_sec": 100.9,
      "up_price": 0.755,
      "down_price": 0.245,
      "arb": null,
      "rv60": 5.227008,
      "eff60": 0.0389,
      "vol_bucket": "HighVol",
      "trend_bucket": "Trend",
      "spread": 0.02,
      "dir_60pct": 0.7244,
      "dir_80pct": 0.7525,
      "dir_90pct": 0.7665,
      "prob_008": 0.36,
      "prob_012": 0.47,
      "prob_020": 0.63
    },
    "ETH": {
      "symbol": "ETH",
      "slug": "eth-updown-15m",
      "condition_id": "0x4ef1503ac5170a2ae28dbbb8f86dddfd4d6ba4b7f8feb69e4ca8c792c33547ab",
      "elapsed_pct": 0.8878,
      "remaining_sec": 100.9,
      "up_price": 0.79,
      "down_price": 0.21,
      "arb": null,
      "rv60": 9.39571,
      "eff60": 0.0264,
      "vol_bucket": "HighVol",
      "trend_bucket": "Trend",
      "spread": 0.04,
      "dir_60pct": 0.7552,
      "dir_80pct": 0.7871,
      "dir_90pct": 0.8031,
      "prob_008": 0.36,
      "prob_012": 0.47,
      "prob_020": 0.63
    },
    "SOL": {
      "symbol": "SOL",
      "slug": "sol-updown-15m",
      "condition_id": "0xb4b9a6c40b65c7ff53ae592aa117b003bc8ac8b9cf95388afd9076b6aec6ed92",
      "elapsed_pct": 0.8878,
      "remaining_sec": 100.9,
      "up_price": 0.11,
      "down_price": 0.89,
      "arb": null,
      "rv60": 6.771476,
      "eff60": 0.0073,
      "vol_bucket": "HighVol",
      "trend_bucket": "Range",
      "spread": 0.04,
      "dir_60pct": 0.2504,
      "dir_80pct": 0.2192,
      "dir_90pct": 0.2036,
      "prob_008": 0.44,
      "prob_012": 0.56,
      "prob_020": 0.71
    },
    "XRP": {
      "symbol": "XRP",
      "slug": "xrp-updown-15m",
      "condition_id": "0x433d8c6908af6cb1ad2edc12ab9730322381c2973a10a189167218fb9c011422",
      "elapsed_pct": 0.8878,
      "remaining_sec": 100.9,
      "up_price": 0.89,
      "down_price": 0.11,
      "arb": null,
      "rv60": 12.448592,
      "eff60": 0.0166,
      "vol_bucket": "HighVol",
      "trend_bucket": "Range",
      "spread": 1.96,
      "dir_60pct": 0.7496,
      "dir_80pct": 0.7808,
      "dir_90pct": 0.7964,
      "prob_008": 0.44,
      "prob_012": 0.56,
      "prob_020": 0.71
    }
  }
}