{
  "updated": "2026-03-14 06:25 PM ET",
  "data": {
    "BTC": {
      "symbol": "BTC",
      "slug": "btc-updown-15m-1773526500",
      "condition_id": "0xd22f228c136c378b22c8f5b489e4863f9ab5893d6bbeee11567ee7a709eba926",
      "elapsed_pct": 0.6683,
      "remaining_sec": 298.5,
      "up_price": 0.465,
      "down_price": 0.535,
      "arb": null,
      "rv60": 690.57623,
      "eff60": 0.007,
      "vol_bucket": "HighVol",
      "trend_bucket": "Range",
      "spread": 98,
      "dir_60pct": 0.4801,
      "dir_80pct": 0.4787,
      "dir_90pct": 0.4773,
      "prob_008": 0.47,
      "prob_012": 0.47,
      "prob_020": 0.51
    },
    "ETH": {
      "symbol": "ETH",
      "slug": "eth-updown-15m-1773526500",
      "condition_id": "0x3c22f9ac6d44cfcd78ab4142d951ae51b33418b10c03edba5f0371765a1764b4",
      "elapsed_pct": 0.6683,
      "remaining_sec": 298.5,
      "up_price": 0.655,
      "down_price": 0.345,
      "arb": null,
      "rv60": 889.64708,
      "eff60": 0.006,
      "vol_bucket": "HighVol",
      "trend_bucket": "Range",
      "spread": 98,
      "dir_60pct": 0.5881,
      "dir_80pct": 0.5943,
      "dir_90pct": 0.6005,
      "prob_008": 0.64,
      "prob_012": 0.66,
      "prob_020": 0.72
    },
    "SOL": {
      "symbol": "SOL",
      "slug": "sol-updown-15m-1773526500",
      "condition_id": "0x34a94a9b113cc37cfaa32ced9b43621398c182980975770bf43c626324b31332",
      "elapsed_pct": 0.6683,
      "remaining_sec": 298.5,
      "up_price": 0.425,
      "down_price": 0.575,
      "arb": null,
      "rv60": 858.3094,
      "eff60": 0.006,
      "vol_bucket": "HighVol",
      "trend_bucket": "Range",
      "spread": 98,
      "dir_60pct": 0.4574,
      "dir_80pct": 0.4544,
      "dir_90pct": 0.4514,
      "prob_008": 0.43,
      "prob_012": 0.42,
      "prob_020": 0.47
    },
    "XRP": {
      "symbol": "XRP",
      "slug": "xrp-updown-15m-1773526500",
      "condition_id": "0xe5334b9bed98eafdf66ab7d2d2e0d08e7d7215021456d91ac6af959c13aeffb3",
      "elapsed_pct": 0.6683,
      "remaining_sec": 298.5,
      "up_price": 0.755,
      "down_price": 0.245,
      "arb": null,
      "rv60": 932.05812,
      "eff60": 0.002,
      "vol_bucket": "HighVol",
      "trend_bucket": "Range",
      "spread": 98,
      "dir_60pct": 0.6449,
      "dir_80pct": 0.6551,
      "dir_90pct": 0.6653,
      "prob_008": 0.73,
      "prob_012": 0.76,
      "prob_020": 0.83
    }
  }
}