{
  "updated": "2026-02-28T17:47:33Z",
  "data": {
    "BTC": {
      "symbol": "BTC",
      "condition_id": "0x22fccae71a1da6d0c2fd2b7878ef147321135e6cbb7e112cb320fc78610c02c5",
      "elapsed_pct": 0.1709,
      "remaining_sec": 746.2,
      "up_price": 0.5,
      "down_price": 0.5,
      "arb": null,
      "rv60": 1.527451,
      "eff60": 0.2,
      "vol_bucket": "HighVol",
      "trend_bucket": "Trend",
      "up_price_ob": 0.5,
      "down_price_ob": 0.5,
      "spread": 1.96,
      "dir_60pct": 0.5,
      "dir_80pct": 0.5,
      "dir_90pct": 0.5,
      "prob_008": 0.36,
      "prob_012": 0.47,
      "prob_020": 0.63
    },
    "ETH": {
      "symbol": "ETH",
      "condition_id": "0xcfef1dc7d437ccc649730227c3f535d45bc57c7b4e65aa2bd365cffbc6f11393",
      "elapsed_pct": 0.1709,
      "remaining_sec": 746.2,
      "up_price": 0.5,
      "down_price": 0.5,
      "arb": null,
      "rv60": 1.695406,
      "eff60": 0.0,
      "vol_bucket": "HighVol",
      "trend_bucket": "Range",
      "up_price_ob": 0.5,
      "down_price_ob": 0.5,
      "spread": 1.96,
      "dir_60pct": 0.5,
      "dir_80pct": 0.5,
      "dir_90pct": 0.5,
      "prob_008": 0.44,
      "prob_012": 0.56,
      "prob_020": 0.71
    },
    "SOL": {
      "symbol": "SOL",
      "condition_id": "0x33375028076aacc733ac5bb51b0e7fcf56579a9a0dfdf31ef0782e8521ab1598",
      "elapsed_pct": 0.1709,
      "remaining_sec": 746.2,
      "up_price": 0.5,
      "down_price": 0.5,
      "arb": null,
      "rv60": 1.831248,
      "eff60": 0.1429,
      "vol_bucket": "HighVol",
      "trend_bucket": "Trend",
      "up_price_ob": 0.5,
      "down_price_ob": 0.5,
      "spread": 1.96,
      "dir_60pct": 0.5,
      "dir_80pct": 0.5,
      "dir_90pct": 0.5,
      "prob_008": 0.36,
      "prob_012": 0.47,
      "prob_020": 0.63
    },
    "XRP": {
      "symbol": "XRP",
      "condition_id": "0x0013cf3cc3802b20f095cfd9d57d197bdfd85f73cd343410cd2914954288576e",
      "elapsed_pct": 0.1709,
      "remaining_sec": 746.2,
      "up_price": 0.5,
      "down_price": 0.5,
      "arb": null,
      "rv60": 1.183158,
      "eff60": 0.3333,
      "vol_bucket": "HighVol",
      "trend_bucket": "Trend",
      "up_price_ob": 0.5,
      "down_price_ob": 0.5,
      "spread": 1.96,
      "dir_60pct": 0.5,
      "dir_80pct": 0.5,
      "dir_90pct": 0.5,
      "prob_008": 0.36,
      "prob_012": 0.47,
      "prob_020": 0.63
    }
  }
}