{
  "updated": "2026-03-07 03:13:40 PM ET",
  "data": {
    "BTC": {
      "symbol": "BTC",
      "slug": "btc-updown-15m",
      "condition_id": "0x9f022db2cbaaf53fc4ed84c2e9d35feec316d321f4cfa422098f7694ea71d4c3",
      "elapsed_pct": 0.9121,
      "remaining_sec": 79.1,
      "up_price": 0.001,
      "down_price": 0.999,
      "arb": null,
      "rv60": 29.953434,
      "eff60": 0.0169,
      "vol_bucket": "HighVol",
      "trend_bucket": "Trend",
      "spread": 1.996,
      "dir_60pct": 0.0609,
      "dir_80pct": 0.006,
      "dir_90pct": 0.0,
      "prob_008": 0.36,
      "prob_012": 0.47,
      "prob_020": 0.63
    },
    "ETH": {
      "symbol": "ETH",
      "slug": "eth-updown-15m",
      "condition_id": "0xd683e066608af0d88c6f1c19d89bc7aea207b9b60a60b94213c8b9b05bf58982",
      "elapsed_pct": 0.9121,
      "remaining_sec": 79.1,
      "up_price": 0.001,
      "down_price": 0.999,
      "arb": null,
      "rv60": 44.405668,
      "eff60": 0.0,
      "vol_bucket": "HighVol",
      "trend_bucket": "Range",
      "spread": 0.0,
      "dir_60pct": 0.1806,
      "dir_80pct": 0.1407,
      "dir_90pct": 0.1208,
      "prob_008": 0.44,
      "prob_012": 0.56,
      "prob_020": 0.71
    },
    "SOL": {
      "symbol": "SOL",
      "slug": "sol-updown-15m",
      "condition_id": "0x927a57791c650930c114573527eb76f9662709dd6b5616e5734097b774eeef03",
      "elapsed_pct": 0.9121,
      "remaining_sec": 79.1,
      "up_price": 0.998,
      "down_price": 0.002,
      "arb": null,
      "rv60": 8.270406,
      "eff60": 0.0406,
      "vol_bucket": "LowVol",
      "trend_bucket": "Trend",
      "spread": 0.0,
      "dir_60pct": 0.9183,
      "dir_80pct": 0.9706,
      "dir_90pct": 0.9968,
      "prob_008": 0.52,
      "prob_012": 0.63,
      "prob_020": 0.8
    },
    "XRP": {
      "symbol": "XRP",
      "slug": "xrp-updown-15m",
      "condition_id": "0xeb19a8af5e3673cc768b0188727dad1b9cc3f65274393de03bf10f9189f4b3b3",
      "elapsed_pct": 0.9121,
      "remaining_sec": 79.1,
      "up_price": 0.001,
      "down_price": 0.999,
      "arb": null,
      "rv60": 24.420772,
      "eff60": 0.0208,
      "vol_bucket": "HighVol",
      "trend_bucket": "Trend",
      "spread": 1.996,
      "dir_60pct": 0.0609,
      "dir_80pct": 0.006,
      "dir_90pct": 0.0,
      "prob_008": 0.36,
      "prob_012": 0.47,
      "prob_020": 0.63
    }
  }
}