{
  "updated": "2026-03-12 01:56:46 AM ET",
  "data": {
    "BTC": {
      "symbol": "BTC",
      "slug": "btc-updown-15m",
      "condition_id": "0xfa2fbba956060fde32562a2ce1ab316dd482ebf9e61803c62ab021f571b2f62f",
      "elapsed_pct": 0.7849,
      "remaining_sec": 193.6,
      "up_price": 0.811,
      "down_price": 0.189,
      "arb": null,
      "rv60": 4.971382,
      "eff60": 0.0007,
      "vol_bucket": "LowVol",
      "trend_bucket": "Range",
      "spread": 1.96,
      "dir_60pct": 0.7239,
      "dir_80pct": 0.7519,
      "dir_90pct": 0.7659,
      "prob_008": 0.65,
      "prob_012": 0.74,
      "prob_020": 0.87
    },
    "ETH": {
      "symbol": "ETH",
      "slug": "eth-updown-15m",
      "condition_id": "0x0c678117ac42d96e8acff56393725e094c896915ae5f757652d56b89e582a81b",
      "elapsed_pct": 0.7849,
      "remaining_sec": 193.6,
      "up_price": 0.241,
      "down_price": 0.759,
      "arb": null,
      "rv60": 6.044446,
      "eff60": 0.0375,
      "vol_bucket": "LowVol",
      "trend_bucket": "Trend",
      "spread": 1.96,
      "dir_60pct": 0.2824,
      "dir_80pct": 0.2552,
      "dir_90pct": 0.2416,
      "prob_008": 0.52,
      "prob_012": 0.63,
      "prob_020": 0.8
    },
    "SOL": {
      "symbol": "SOL",
      "slug": "sol-updown-15m",
      "condition_id": "0x8cfaaf46be6deef3e4023012d87a118c26c2cc637dd64064d8c45eb859d61fd0",
      "elapsed_pct": 0.7849,
      "remaining_sec": 193.6,
      "up_price": 0.05,
      "down_price": 0.95,
      "arb": null,
      "rv60": 9.085236,
      "eff60": 0.02,
      "vol_bucket": "LowVol",
      "trend_bucket": "Trend",
      "spread": 1.96,
      "dir_60pct": 0.122,
      "dir_80pct": 0.0747,
      "dir_90pct": 0.0511,
      "prob_008": 0.52,
      "prob_012": 0.63,
      "prob_020": 0.8
    },
    "XRP": {
      "symbol": "XRP",
      "slug": "xrp-updown-15m",
      "condition_id": "0x57f128b91eb165b24fbc8d9c8b77b300e55261c5f16037c2bb370358eb216263",
      "elapsed_pct": 0.7849,
      "remaining_sec": 193.6,
      "up_price": 0.94,
      "down_price": 0.06,
      "arb": null,
      "rv60": 8.416054,
      "eff60": 0.0081,
      "vol_bucket": "HighVol",
      "trend_bucket": "Range",
      "spread": 1.96,
      "dir_60pct": 0.7816,
      "dir_80pct": 0.8168,
      "dir_90pct": 0.8344,
      "prob_008": 0.44,
      "prob_012": 0.56,
      "prob_020": 0.71
    }
  }
}