{
  "updated": "2026-03-01T19:23:34Z",
  "data": {
    "BTC": {
      "symbol": "BTC",
      "condition_id": "0x27cb032f7f5a44e61f5e42179934afc35ce28f4449a8d246212ed75bb34f6026",
      "elapsed_pct": 0.5721,
      "remaining_sec": 385.1,
      "up_price": 0.501,
      "down_price": 0.501,
      "arb": null,
      "rv60": 0.969035,
      "eff60": 0.0124,
      "vol_bucket": "LowVol",
      "trend_bucket": "Range",
      "up_price_ob": 0.501,
      "down_price_ob": 0.501,
      "spread": 1.96,
      "dir_60pct": 0.5007,
      "dir_80pct": 0.5008,
      "dir_90pct": 0.5009,
      "prob_008": 0.65,
      "prob_012": 0.74,
      "prob_020": 0.87
    },
    "ETH": {
      "symbol": "ETH",
      "condition_id": "0xb63d6ad85ece156dec2d0a5feb3e70520e7be8838a45178c6382ef26dc570c60",
      "elapsed_pct": 0.5721,
      "remaining_sec": 385.1,
      "up_price": 0.67,
      "down_price": 0.67,
      "arb": null,
      "rv60": 2.276313,
      "eff60": 0.0321,
      "vol_bucket": "LowVol",
      "trend_bucket": "Trend",
      "up_price_ob": 0.67,
      "down_price_ob": 0.67,
      "spread": 1.96,
      "dir_60pct": 0.6428,
      "dir_80pct": 0.6607,
      "dir_90pct": 0.6696,
      "prob_008": 0.52,
      "prob_012": 0.63,
      "prob_020": 0.8
    },
    "SOL": {
      "symbol": "SOL",
      "condition_id": "0x50080f7f264194010445e5a8f74595f2c805a61ec1cd53ebdfea5139a7b0a0cc",
      "elapsed_pct": 0.5721,
      "remaining_sec": 385.1,
      "up_price": 0.67,
      "down_price": 0.67,
      "arb": null,
      "rv60": 1.574225,
      "eff60": 0.0509,
      "vol_bucket": "LowVol",
      "trend_bucket": "Trend",
      "up_price_ob": 0.67,
      "down_price_ob": 0.67,
      "spread": 1.96,
      "dir_60pct": 0.6428,
      "dir_80pct": 0.6607,
      "dir_90pct": 0.6696,
      "prob_008": 0.52,
      "prob_012": 0.63,
      "prob_020": 0.8
    },
    "XRP": {
      "symbol": "XRP",
      "condition_id": "0x6b64947e4b479c92e2334a16171bcc0dc7a3342976f0f30b567be934609475a8",
      "elapsed_pct": 0.5721,
      "remaining_sec": 385.1,
      "up_price": 0.5,
      "down_price": 0.5,
      "arb": null,
      "rv60": 0.709133,
      "eff60": 0.0341,
      "vol_bucket": "LowVol",
      "trend_bucket": "Trend",
      "up_price_ob": 0.5,
      "down_price_ob": 0.5,
      "spread": 1.96,
      "dir_60pct": 0.5,
      "dir_80pct": 0.5,
      "dir_90pct": 0.5,
      "prob_008": 0.52,
      "prob_012": 0.63,
      "prob_020": 0.8
    }
  }
}