{
  "updated": "2026-03-03T14:35:35Z",
  "data": {
    "BTC": {
      "symbol": "BTC",
      "condition_id": "0x7e1ee9fc97e3a7dcf3cf3461e7ef7f79c45fb8ab7bd6319fb091eb9f61e561fb",
      "elapsed_pct": 0.373,
      "remaining_sec": 564.3,
      "up_price": 0.74,
      "down_price": 0.74,
      "arb": null,
      "rv60": 3.467639,
      "eff60": 0.0261,
      "vol_bucket": "LowVol",
      "trend_bucket": "Trend",
      "up_price_ob": 0.74,
      "down_price_ob": 0.74,
      "spread": 1.96,
      "dir_60pct": 0.7016,
      "dir_80pct": 0.7268,
      "dir_90pct": 0.7394,
      "prob_008": 0.52,
      "prob_012": 0.63,
      "prob_020": 0.8
    },
    "ETH": {
      "symbol": "ETH",
      "condition_id": "0x7241bb2a9701502f543f41fb75eb88f915694c2fb3e4e4fd3aa5a730b77a0091",
      "elapsed_pct": 0.373,
      "remaining_sec": 564.3,
      "up_price": 0.21,
      "down_price": 0.21,
      "arb": null,
      "rv60": 4.547076,
      "eff60": 0.0008,
      "vol_bucket": "LowVol",
      "trend_bucket": "Range",
      "up_price_ob": 0.21,
      "down_price_ob": 0.21,
      "spread": 1.96,
      "dir_60pct": 0.2912,
      "dir_80pct": 0.2651,
      "dir_90pct": 0.252,
      "prob_008": 0.65,
      "prob_012": 0.74,
      "prob_020": 0.87
    },
    "SOL": {
      "symbol": "SOL",
      "condition_id": "0x34a8c64ce85d3d483a6a99621ab5558d1d82ab89eec2ee65b5fac9c91f0b55e5",
      "elapsed_pct": 0.373,
      "remaining_sec": 564.3,
      "up_price": 0.28,
      "down_price": 0.28,
      "arb": null,
      "rv60": 3.574443,
      "eff60": 0.0314,
      "vol_bucket": "LowVol",
      "trend_bucket": "Trend",
      "up_price_ob": 0.28,
      "down_price_ob": 0.28,
      "spread": 1.96,
      "dir_60pct": 0.3152,
      "dir_80pct": 0.2921,
      "dir_90pct": 0.2806,
      "prob_008": 0.52,
      "prob_012": 0.63,
      "prob_020": 0.8
    },
    "XRP": {
      "symbol": "XRP",
      "condition_id": "0x0b54163a6c9c704980ab45a1ed3273e7bf47ab4166b9568111183b5b4ad00715",
      "elapsed_pct": 0.373,
      "remaining_sec": 564.3,
      "up_price": 0.54,
      "down_price": 0.54,
      "arb": null,
      "rv60": 2.192538,
      "eff60": 0.0083,
      "vol_bucket": "LowVol",
      "trend_bucket": "Range",
      "up_price_ob": 0.54,
      "down_price_ob": 0.54,
      "spread": 1.96,
      "dir_60pct": 0.5288,
      "dir_80pct": 0.5324,
      "dir_90pct": 0.5342,
      "prob_008": 0.65,
      "prob_012": 0.74,
      "prob_020": 0.87
    }
  }
}