{
  "updated": "2026-03-11 07:54:37 AM ET",
  "data": [
    {
      "symbol": "ETH",
      "slug": "eth-updown-15m",
      "outcome": "DOWN",
      "side": "BUY",
      "size": 5.0,
      "price": 0.78,
      "confidence": 0.76,
      "trigger": "trend_follow",
      "reason": "TREND FOLLOW (HighVol+Trend, 61% elapsed) \u2014 DOWN token at 0.780 deviates 0.260 from 0.50. Momentum continuation strategy: buying the already-winning leg. Fixed $5 USDC stake."
    },
    {
      "symbol": "SOL",
      "slug": "sol-updown-15m",
      "outcome": "DOWN",
      "side": "BUY",
      "size": 5.0,
      "price": 0.99,
      "confidence": 0.695,
      "trigger": "trend_follow",
      "reason": "TREND FOLLOW (HighVol+Trend, 61% elapsed) \u2014 DOWN token at 0.990 deviates 0.195 from 0.50. Momentum continuation strategy: buying the already-winning leg. Fixed $5 USDC stake."
    },
    {
      "symbol": "ETH",
      "slug": "eth-updown-15m",
      "outcome": "DOWN",
      "side": "BUY",
      "size": 5.0,
      "price": 0.82,
      "confidence": 0.815,
      "trigger": "trend_follow",
      "reason": "TREND FOLLOW (HighVol+Trend, 61% elapsed) \u2014 DOWN token at 0.820 deviates 0.315 from 0.50. Momentum continuation strategy: buying the already-winning leg. Fixed $5 USDC stake."
    },
    {
      "symbol": "SOL",
      "slug": "sol-updown-15m",
      "outcome": "DOWN",
      "side": "BUY",
      "size": 5.0,
      "price": 0.75,
      "confidence": 0.745,
      "trigger": "trend_follow",
      "reason": "TREND FOLLOW (HighVol+Trend, 61% elapsed) \u2014 DOWN token at 0.750 deviates 0.245 from 0.50. Momentum continuation strategy: buying the already-winning leg. Fixed $5 USDC stake."
    },
    {
      "symbol": "ETH",
      "slug": "eth-updown-15m",
      "outcome": "DOWN",
      "side": "BUY",
      "size": 5.0,
      "price": 0.8,
      "confidence": 0.82,
      "trigger": "trend_follow",
      "reason": "TREND FOLLOW (HighVol+Trend, 61% elapsed) \u2014 DOWN token at 0.800 deviates 0.320 from 0.50. Momentum continuation strategy: buying the already-winning leg. Fixed $5 USDC stake."
    },
    {
      "symbol": "SOL",
      "slug": "sol-updown-15m",
      "outcome": "DOWN",
      "side": "BUY",
      "size": 5.0,
      "price": 0.75,
      "confidence": 0.745,
      "trigger": "trend_follow",
      "reason": "TREND FOLLOW (HighVol+Trend, 61% elapsed) \u2014 DOWN token at 0.750 deviates 0.245 from 0.50. Momentum continuation strategy: buying the already-winning leg. Fixed $5 USDC stake."
    },
    {
      "symbol": "ETH",
      "slug": "eth-updown-15m",
      "outcome": "DOWN",
      "side": "BUY",
      "size": 5.0,
      "price": 0.81,
      "confidence": 0.795,
      "trigger": "trend_follow",
      "reason": "TREND FOLLOW (HighVol+Trend, 62% elapsed) \u2014 DOWN token at 0.810 deviates 0.295 from 0.50. Momentum continuation strategy: buying the already-winning leg. Fixed $5 USDC stake."
    },
    {
      "symbol": "ETH",
      "slug": "eth-updown-15m",
      "outcome": "DOWN",
      "side": "BUY",
      "size": 5.0,
      "price": 0.81,
      "confidence": 0.795,
      "trigger": "trend_follow",
      "reason": "TREND FOLLOW (HighVol+Trend, 62% elapsed) \u2014 DOWN token at 0.810 deviates 0.295 from 0.50. Momentum continuation strategy: buying the already-winning leg. Fixed $5 USDC stake."
    },
    {
      "symbol": "ETH",
      "slug": "eth-updown-15m",
      "outcome": "DOWN",
      "side": "BUY",
      "size": 5.0,
      "price": 0.78,
      "confidence": 0.795,
      "trigger": "trend_follow",
      "reason": "TREND FOLLOW (HighVol+Trend, 62% elapsed) \u2014 DOWN token at 0.780 deviates 0.295 from 0.50. Momentum continuation strategy: buying the already-winning leg. Fixed $5 USDC stake."
    },
    {
      "symbol": "ETH",
      "slug": "eth-updown-15m",
      "outcome": "DOWN",
      "side": "BUY",
      "size": 5.0,
      "price": 0.77,
      "confidence": 0.77,
      "trigger": "trend_follow",
      "reason": "TREND FOLLOW (HighVol+Trend, 63% elapsed) \u2014 DOWN token at 0.770 deviates 0.270 from 0.50. Momentum continuation strategy: buying the already-winning leg. Fixed $5 USDC stake."
    },
    {
      "symbol": "XRP",
      "slug": "xrp-updown-15m",
      "outcome": "DOWN",
      "side": "BUY",
      "size": 5.0,
      "price": 0.8,
      "confidence": 0.785,
      "trigger": "trend_follow",
      "reason": "TREND FOLLOW (HighVol+Trend, 63% elapsed) \u2014 DOWN token at 0.800 deviates 0.285 from 0.50. Momentum continuation strategy: buying the already-winning leg. Fixed $5 USDC stake."
    },
    {
      "symbol": "BTC",
      "slug": "btc-updown-15m",
      "outcome": "UP",
      "side": "BUY",
      "size": 5.0,
      "price": 0.48,
      "confidence": 0.52,
      "trigger": "pre_open",
      "reason": "PRE-OPEN limit order \u2014 329s before market start. Buying UP at 0.48 (below ~0.50 fair value). Current regime: HighVol+Range."
    },
    {
      "symbol": "BTC",
      "slug": "btc-updown-15m",
      "outcome": "DOWN",
      "side": "BUY",
      "size": 5.0,
      "price": 0.48,
      "confidence": 0.52,
      "trigger": "pre_open",
      "reason": "PRE-OPEN limit order \u2014 329s before market start. Buying DOWN at 0.48 (below ~0.50 fair value). Current regime: HighVol+Range."
    },
    {
      "symbol": "ETH",
      "slug": "eth-updown-15m",
      "outcome": "UP",
      "side": "BUY",
      "size": 5.0,
      "price": 0.48,
      "confidence": 0.52,
      "trigger": "pre_open",
      "reason": "PRE-OPEN limit order \u2014 329s before market start. Buying UP at 0.48 (below ~0.50 fair value). Current regime: HighVol+Range."
    },
    {
      "symbol": "ETH",
      "slug": "eth-updown-15m",
      "outcome": "DOWN",
      "side": "BUY",
      "size": 5.0,
      "price": 0.48,
      "confidence": 0.52,
      "trigger": "pre_open",
      "reason": "PRE-OPEN limit order \u2014 329s before market start. Buying DOWN at 0.48 (below ~0.50 fair value). Current regime: HighVol+Range."
    },
    {
      "symbol": "SOL",
      "slug": "sol-updown-15m",
      "outcome": "UP",
      "side": "BUY",
      "size": 5.0,
      "price": 0.48,
      "confidence": 0.52,
      "trigger": "pre_open",
      "reason": "PRE-OPEN limit order \u2014 329s before market start. Buying UP at 0.48 (below ~0.50 fair value). Current regime: HighVol+Range."
    },
    {
      "symbol": "SOL",
      "slug": "sol-updown-15m",
      "outcome": "DOWN",
      "side": "BUY",
      "size": 5.0,
      "price": 0.48,
      "confidence": 0.52,
      "trigger": "pre_open",
      "reason": "PRE-OPEN limit order \u2014 329s before market start. Buying DOWN at 0.48 (below ~0.50 fair value). Current regime: HighVol+Range."
    },
    {
      "symbol": "XRP",
      "slug": "xrp-updown-15m",
      "outcome": "UP",
      "side": "BUY",
      "size": 5.0,
      "price": 0.48,
      "confidence": 0.52,
      "trigger": "pre_open",
      "reason": "PRE-OPEN limit order \u2014 329s before market start. Buying UP at 0.48 (below ~0.50 fair value). Current regime: HighVol+Trend."
    },
    {
      "symbol": "XRP",
      "slug": "xrp-updown-15m",
      "outcome": "DOWN",
      "side": "BUY",
      "size": 5.0,
      "price": 0.48,
      "confidence": 0.52,
      "trigger": "pre_open",
      "reason": "PRE-OPEN limit order \u2014 329s before market start. Buying DOWN at 0.48 (below ~0.50 fair value). Current regime: HighVol+Trend."
    },
    {
      "symbol": "XRP",
      "slug": "xrp-updown-15m",
      "outcome": "DOWN",
      "side": "BUY",
      "size": 5.0,
      "price": 0.99,
      "confidence": 0.79,
      "trigger": "trend_follow",
      "reason": "TREND FOLLOW (HighVol+Trend, 63% elapsed) \u2014 DOWN token at 0.990 deviates 0.290 from 0.50. Momentum continuation strategy: buying the already-winning leg. Fixed $5 USDC stake."
    }
  ]
}