{
  "updated": "2026-03-10 06:56:01 AM ET",
  "data": [
    {
      "symbol": "ETH",
      "slug": "eth-updown-15m",
      "outcome": "UP",
      "side": "BUY",
      "size": 5.0,
      "price": 0.48,
      "confidence": 0.52,
      "trigger": "pre_open",
      "reason": "PRE-OPEN limit order \u2014 330s before market start. Buying UP at 0.48 (below ~0.50 fair value). Current regime: HighVol+Trend."
    },
    {
      "symbol": "ETH",
      "slug": "eth-updown-15m",
      "outcome": "DOWN",
      "side": "BUY",
      "size": 5.0,
      "price": 0.48,
      "confidence": 0.52,
      "trigger": "pre_open",
      "reason": "PRE-OPEN limit order \u2014 330s before market start. Buying DOWN at 0.48 (below ~0.50 fair value). Current regime: HighVol+Trend."
    },
    {
      "symbol": "ETH",
      "slug": "eth-updown-15m",
      "outcome": "UP",
      "side": "BUY",
      "size": 5.0,
      "price": 0.99,
      "confidence": 0.986,
      "trigger": "trend_follow",
      "reason": "TREND FOLLOW (HighVol+Trend, 63% elapsed) \u2014 UP token at 0.990 deviates 0.486 from 0.50. Momentum continuation strategy: buying the already-winning leg. Fixed $5 USDC stake."
    },
    {
      "symbol": "SOL",
      "slug": "sol-updown-15m",
      "outcome": "UP",
      "side": "BUY",
      "size": 5.0,
      "price": 0.48,
      "confidence": 0.52,
      "trigger": "pre_open",
      "reason": "PRE-OPEN limit order \u2014 330s before market start. Buying UP at 0.48 (below ~0.50 fair value). Current regime: HighVol+Range."
    },
    {
      "symbol": "SOL",
      "slug": "sol-updown-15m",
      "outcome": "DOWN",
      "side": "BUY",
      "size": 5.0,
      "price": 0.48,
      "confidence": 0.52,
      "trigger": "pre_open",
      "reason": "PRE-OPEN limit order \u2014 330s before market start. Buying DOWN at 0.48 (below ~0.50 fair value). Current regime: HighVol+Range."
    },
    {
      "symbol": "XRP",
      "slug": "xrp-updown-15m",
      "outcome": "UP",
      "side": "BUY",
      "size": 5.0,
      "price": 0.48,
      "confidence": 0.52,
      "trigger": "pre_open",
      "reason": "PRE-OPEN limit order \u2014 330s before market start. Buying UP at 0.48 (below ~0.50 fair value). Current regime: LowVol+Range."
    },
    {
      "symbol": "XRP",
      "slug": "xrp-updown-15m",
      "outcome": "DOWN",
      "side": "BUY",
      "size": 5.0,
      "price": 0.48,
      "confidence": 0.52,
      "trigger": "pre_open",
      "reason": "PRE-OPEN limit order \u2014 330s before market start. Buying DOWN at 0.48 (below ~0.50 fair value). Current regime: LowVol+Range."
    },
    {
      "symbol": "ETH",
      "slug": "eth-updown-15m",
      "outcome": "UP",
      "side": "BUY",
      "size": 5.0,
      "price": 0.99,
      "confidence": 0.986,
      "trigger": "trend_follow",
      "reason": "TREND FOLLOW (HighVol+Trend, 64% elapsed) \u2014 UP token at 0.990 deviates 0.486 from 0.50. Momentum continuation strategy: buying the already-winning leg. Fixed $5 USDC stake."
    },
    {
      "symbol": "ETH",
      "slug": "eth-updown-15m",
      "outcome": "UP",
      "side": "BUY",
      "size": 5.0,
      "price": 0.99,
      "confidence": 0.986,
      "trigger": "trend_follow",
      "reason": "TREND FOLLOW (HighVol+Trend, 64% elapsed) \u2014 UP token at 0.990 deviates 0.486 from 0.50. Momentum continuation strategy: buying the already-winning leg. Fixed $5 USDC stake."
    },
    {
      "symbol": "ETH",
      "slug": "eth-updown-15m",
      "outcome": "UP",
      "side": "BUY",
      "size": 5.0,
      "price": 0.999,
      "confidence": 0.986,
      "trigger": "trend_follow",
      "reason": "TREND FOLLOW (HighVol+Trend, 64% elapsed) \u2014 UP token at 0.999 deviates 0.486 from 0.50. Momentum continuation strategy: buying the already-winning leg. Fixed $5 USDC stake."
    },
    {
      "symbol": "ETH",
      "slug": "eth-updown-15m",
      "outcome": "UP",
      "side": "BUY",
      "size": 5.0,
      "price": 0.99,
      "confidence": 0.986,
      "trigger": "trend_follow",
      "reason": "TREND FOLLOW (HighVol+Trend, 65% elapsed) \u2014 UP token at 0.990 deviates 0.486 from 0.50. Momentum continuation strategy: buying the already-winning leg. Fixed $5 USDC stake."
    },
    {
      "symbol": "ETH",
      "slug": "eth-updown-15m",
      "outcome": "UP",
      "side": "BUY",
      "size": 5.0,
      "price": 0.99,
      "confidence": 0.986,
      "trigger": "trend_follow",
      "reason": "TREND FOLLOW (HighVol+Trend, 65% elapsed) \u2014 UP token at 0.990 deviates 0.486 from 0.50. Momentum continuation strategy: buying the already-winning leg. Fixed $5 USDC stake."
    },
    {
      "symbol": "ETH",
      "slug": "eth-updown-15m",
      "outcome": "UP",
      "side": "BUY",
      "size": 5.0,
      "price": 0.99,
      "confidence": 0.986,
      "trigger": "trend_follow",
      "reason": "TREND FOLLOW (HighVol+Trend, 65% elapsed) \u2014 UP token at 0.990 deviates 0.486 from 0.50. Momentum continuation strategy: buying the already-winning leg. Fixed $5 USDC stake."
    },
    {
      "symbol": "ETH",
      "slug": "eth-updown-15m",
      "outcome": "UP",
      "side": "BUY",
      "size": 5.0,
      "price": 0.99,
      "confidence": 0.986,
      "trigger": "trend_follow",
      "reason": "TREND FOLLOW (HighVol+Trend, 65% elapsed) \u2014 UP token at 0.990 deviates 0.486 from 0.50. Momentum continuation strategy: buying the already-winning leg. Fixed $5 USDC stake."
    },
    {
      "symbol": "ETH",
      "slug": "eth-updown-15m",
      "outcome": "UP",
      "side": "BUY",
      "size": 5.0,
      "price": 0.99,
      "confidence": 0.989,
      "trigger": "trend_follow",
      "reason": "TREND FOLLOW (HighVol+Trend, 69% elapsed) \u2014 UP token at 0.990 deviates 0.489 from 0.50. Momentum continuation strategy: buying the already-winning leg. Fixed $5 USDC stake."
    },
    {
      "symbol": "ETH",
      "slug": "eth-updown-15m",
      "outcome": "UP",
      "side": "BUY",
      "size": 5.0,
      "price": 0.99,
      "confidence": 0.989,
      "trigger": "trend_follow",
      "reason": "TREND FOLLOW (HighVol+Trend, 69% elapsed) \u2014 UP token at 0.990 deviates 0.489 from 0.50. Momentum continuation strategy: buying the already-winning leg. Fixed $5 USDC stake."
    },
    {
      "symbol": "ETH",
      "slug": "eth-updown-15m",
      "outcome": "UP",
      "side": "BUY",
      "size": 5.0,
      "price": 0.99,
      "confidence": 0.989,
      "trigger": "trend_follow",
      "reason": "TREND FOLLOW (HighVol+Trend, 69% elapsed) \u2014 UP token at 0.990 deviates 0.489 from 0.50. Momentum continuation strategy: buying the already-winning leg. Fixed $5 USDC stake."
    },
    {
      "symbol": "SOL",
      "slug": "sol-updown-15m",
      "outcome": "UP",
      "side": "BUY",
      "size": 5.0,
      "price": 0.99,
      "confidence": 0.985,
      "trigger": "trend_follow",
      "reason": "TREND FOLLOW (HighVol+Trend, 69% elapsed) \u2014 UP token at 0.990 deviates 0.485 from 0.50. Momentum continuation strategy: buying the already-winning leg. Fixed $5 USDC stake."
    },
    {
      "symbol": "ETH",
      "slug": "eth-updown-15m",
      "outcome": "UP",
      "side": "BUY",
      "size": 5.0,
      "price": 0.99,
      "confidence": 0.989,
      "trigger": "trend_follow",
      "reason": "TREND FOLLOW (HighVol+Trend, 70% elapsed) \u2014 UP token at 0.990 deviates 0.489 from 0.50. Momentum continuation strategy: buying the already-winning leg. Fixed $5 USDC stake."
    },
    {
      "symbol": "SOL",
      "slug": "sol-updown-15m",
      "outcome": "UP",
      "side": "BUY",
      "size": 5.0,
      "price": 0.99,
      "confidence": 0.985,
      "trigger": "trend_follow",
      "reason": "TREND FOLLOW (HighVol+Trend, 70% elapsed) \u2014 UP token at 0.990 deviates 0.485 from 0.50. Momentum continuation strategy: buying the already-winning leg. Fixed $5 USDC stake."
    }
  ]
}